<?xml version="1.0" encoding="utf-8"?>
<!DOCTYPE hibernate-mapping PUBLIC "-//Hibernate/Hibernate Mapping DTD 3.0//EN"
"http://hibernate.sourceforge.net/hibernate-mapping-3.0.dtd">
<!-- 
    Mapping file autogenerated by MyEclipse Persistence Tools
-->
<hibernate-mapping>
    <class name="com.ycszh.ssh.hbm.yanche.PdasmycSjzd" table="PDASMYC_SJZD">
        <id name="id" type="java.lang.String">
            <column name="ID" length="100" />
        </id>
        <property name="dmz" type="java.lang.String">
            <column name="DMZ" length="30" />
        </property>
        <property name="dmlb" type="java.lang.String">
            <column name="DMLB" length="3" />
        </property>
        <property name="dmsm1" type="java.lang.String">
            <column name="DMSM1" length="64" />
        </property>
        <property name="dmsm2" type="java.lang.String">
            <column name="DMSM2" length="64" />
        </property>
        <property name="dmsm3" type="java.lang.String">
            <column name="DMSM3" length="64" />
        </property>
        <property name="dmsm4" type="java.lang.String">
            <column name="DMSM4" length="64" />
        </property>
    </class>
</hibernate-mapping>
